ntkutils/__init__.py
ntkutils/cfgtools.py
ntkutils-2.2.4.dist-info/LICENSE
ntkutils-2.2.4.dist-info/METADATA
ntkutils-2.2.4.dist-info/WHEEL
ntkutils-2.2.4.dist-info/top_level.txt
ntkutils-2.2.4.dist-info/RECORD
