Metadata-Version: 2.1
Name: ntkutils
Version: 2.2.4
Summary: Utilities for tkinter
Home-page: https://github.com/not-nef/ntkutils
Author: not-nef
License: MIT
Keywords: ntkutils
Platform: UNKNOWN
License-File: LICENSE
Requires-Dist: win32mica
